saatgut/__init__.py
saatgut/_secure_import.py
saatgut/_seed_jax.py
saatgut/_seed_numpy.py
saatgut/_seed_random.py
saatgut/_seed_tensorflow.py
saatgut/_seed_torch.py
saatgut-0.1.2.dist-info/licenses/LICENSE
test/__init__.py
test/numpy_test.py
test/seed_everything_test.py
test/tensorflow_test.py
test/torch_test.py
saatgut-0.1.2.dist-info/METADATA
saatgut-0.1.2.dist-info/WHEEL
saatgut-0.1.2.dist-info/top_level.txt
saatgut-0.1.2.dist-info/RECORD
